pylighthouse/__init__.py
pylighthouse/pylighthouse.py
pylighthouse-0.1.0.dist-info/AUTHORS.rst
pylighthouse-0.1.0.dist-info/LICENSE
pylighthouse-0.1.0.dist-info/METADATA
pylighthouse-0.1.0.dist-info/WHEEL
pylighthouse-0.1.0.dist-info/top_level.txt
pylighthouse-0.1.0.dist-info/RECORD
