Metadata-Version: 2.1
Name: pylighthouse
Version: 0.1.0
Summary: Helps workloads find safe harbor.
Home-page: https://github.com/djhaskin987/pylighthouse
Author: Daniel Jay Haskin
Author-email: djhaskin987@gmail.com
License: Apache Software License 2.0
Keywords: pylighthouse
Platform: UNKNOWN
Classifier: Development Status :: 2 - Pre-Alpha
Classifier: Intended Audience :: Developers
Classifier: License :: OSI Approved :: Apache Software License
Classifier: Natural Language :: English
Classifier: Programming Language :: Python :: 2
Classifier: Programming Language :: Python :: 2.7
Classifier: Programming Language :: Python :: 3
Classifier: Programming Language :: Python :: 3.4
Classifier: Programming Language :: Python :: 3.5
Classifier: Programming Language :: Python :: 3.6
Classifier: Programming Language :: Python :: 3.7
